devopsdemo/__init__.py
devopsdemo-0.1.0.dist-info/METADATA
devopsdemo-0.1.0.dist-info/WHEEL
devopsdemo-0.1.0.dist-info/RECORD
