Metadata-Version: 2.1
Name: devopsdemo
Version: 0.1.0
Summary: 
Author: Nithish Kumar S
Author-email: nithishkumar.2001137@srec.ac.in
Requires-Python: >=3.11,<4.0
Classifier: Programming Language :: Python :: 3
Classifier: Programming Language :: Python :: 3.11
